cmd_colorizer/__init__.py
cmd_colorizer/colorizer.py
cmd_colorizer-0.0.4.dist-info/LICENSE
cmd_colorizer-0.0.4.dist-info/METADATA
cmd_colorizer-0.0.4.dist-info/WHEEL
cmd_colorizer-0.0.4.dist-info/top_level.txt
cmd_colorizer-0.0.4.dist-info/RECORD
